README.md
setup.py
lj_insert_sql.egg-info/PKG-INFO
lj_insert_sql.egg-info/SOURCES.txt
lj_insert_sql.egg-info/dependency_links.txt
lj_insert_sql.egg-info/entry_points.txt
lj_insert_sql.egg-info/top_level.txt
lj_insert_sql.egg-info/.idea/.gitignore
lj_insert_sql.egg-info/.idea/lj_insert_sql.egg-info.iml
lj_insert_sql.egg-info/.idea/misc.xml
lj_insert_sql.egg-info/.idea/modules.xml
lj_insert_sql.egg-info/.idea/workspace.xml
lj_insert_sql.egg-info/.idea/inspectionProfiles/profiles_settings.xml
package/__init__.py
package/base_mysql.py
package/lj_sql_package_old.py
package/lj_sqlpackage.py
package/utils.py
test/__init__.py
test/test.py