Metadata-Version: 2.1
Name: lj-insert-sql
Version: 0.6.7
Summary: lj add sql！
Home-page: http://songbaobao.com
Author: jiaochanghao
Author-email: 2154195820@qq.com
License: MIT Licence
Keywords: test
Platform: any
